faust/__init__.py
faust/__main__.py
faust/auth.py
faust/channels.py
faust/events.py
faust/exceptions.py
faust/joins.py
faust/py.typed
faust/streams.py
faust/topics.py
faust/windows.py
faust/worker.py
faust/_cython/__init__.py
faust/_cython/streams.pyx
faust/_cython/windows.pyx
faust/agents/__init__.py
faust/agents/actor.py
faust/agents/agent.py
faust/agents/manager.py
faust/agents/models.py
faust/agents/replies.py
faust/app/__init__.py
faust/app/_attached.py
faust/app/base.py
faust/app/router.py
faust/assignor/__init__.py
faust/assignor/client_assignment.py
faust/assignor/cluster_assignment.py
faust/assignor/copartitioned_assignor.py
faust/assignor/leader_assignor.py
faust/assignor/partition_assignor.py
faust/cli/__init__.py
faust/cli/agents.py
faust/cli/base.py
faust/cli/clean_versions.py
faust/cli/completion.py
faust/cli/faust.py
faust/cli/livecheck.py
faust/cli/model.py
faust/cli/models.py
faust/cli/params.py
faust/cli/reset.py
faust/cli/send.py
faust/cli/tables.py
faust/cli/worker.py
faust/fixups/__init__.py
faust/fixups/base.py
faust/fixups/django.py
faust/livecheck/__init__.py
faust/livecheck/app.py
faust/livecheck/case.py
faust/livecheck/exceptions.py
faust/livecheck/locals.py
faust/livecheck/models.py
faust/livecheck/runners.py
faust/livecheck/signals.py
faust/livecheck/patches/__init__.py
faust/livecheck/patches/aiohttp.py
faust/models/__init__.py
faust/models/base.py
faust/models/fields.py
faust/models/record.py
faust/models/tags.py
faust/models/typing.py
faust/sensors/__init__.py
faust/sensors/base.py
faust/sensors/datadog.py
faust/sensors/monitor.py
faust/sensors/statsd.py
faust/serializers/__init__.py
faust/serializers/codecs.py
faust/serializers/registry.py
faust/serializers/schemas.py
faust/stores/__init__.py
faust/stores/base.py
faust/stores/memory.py
faust/stores/rocksdb.py
faust/tables/__init__.py
faust/tables/base.py
faust/tables/globaltable.py
faust/tables/manager.py
faust/tables/objects.py
faust/tables/recovery.py
faust/tables/sets.py
twm_faust-1.16.8.dist-info/licenses/LICENSE
twm_faust-1.16.8.dist-info/METADATA
twm_faust-1.16.8.dist-info/WHEEL
twm_faust-1.16.8.dist-info/entry_points.txt
twm_faust-1.16.8.dist-info/top_level.txt
twm_faust-1.16.8.dist-info/RECORD
