Metadata-Version: 2.4
Name: twm-faust
Version: 1.16.8
Summary: Python Stream processing.
Home-page: http://faust.readthedocs.io/
Author: Robinhood Markets, Inc.
Author-email: contact@fauststream.com
License: BSD 3-Clause
Project-URL: Bug Reports, https://github.com/robinhood/faust/issues
Project-URL: Source, https://github.com/robinhood/faust
Project-URL: Documentation, https://faust.readthedocs.io/
Keywords: stream,processing,asyncio,distributed,queue,kafka
Platform: any
Classifier: Framework :: AsyncIO
Classifier: Development Status :: 5 - Production/Stable
Classifier: Intended Audience :: Developers
Classifier: Natural Language :: English
Classifier: License :: OSI Approved :: BSD License
Classifier: Programming Language :: Python
Classifier: Programming Language :: Python :: 3 :: Only
Classifier: Programming Language :: Python :: 3.6
Classifier: Programming Language :: Python :: 3.7
Classifier: Programming Language :: Python :: 3.8
Classifier: Programming Language :: Python :: 3.9
Classifier: Programming Language :: Python :: Implementation :: CPython
Classifier: Programming Language :: Python :: Implementation :: PyPy
Classifier: Operating System :: POSIX
Classifier: Operating System :: POSIX :: Linux
Classifier: Operating System :: MacOS :: MacOS X
Classifier: Operating System :: POSIX :: BSD
Classifier: Operating System :: Microsoft :: Windows
Classifier: Topic :: System :: Networking
Classifier: Topic :: System :: Distributed Computing
Requires-Python: >=3.6.0
License-File: LICENSE
Requires-Dist: aiohttp<4.0,>=3.8.0
Requires-Dist: aiohttp_cors<2.0,>=0.7
Requires-Dist: click<8.0,>=6.7
Requires-Dist: colorclass<3.0,>=2.2
Requires-Dist: mode-streaming<0.4,>=0.3.5
Requires-Dist: opentracing<2.0.0,>=1.3.0
Requires-Dist: terminaltables<4.0,>=3.1
Requires-Dist: venusian<2.0,>=1.1
Requires-Dist: yarl<2.0,>=1.0
Requires-Dist: croniter>=0.3.16
Requires-Dist: mypy_extensions
Requires-Dist: intervaltree==3.1.0
Requires-Dist: psutil==5.8.0
Requires-Dist: aiokafka==0.12.0
Requires-Dist: sortedcontainers>=2.0.0
Provides-Extra: fast
Requires-Dist: aiodns>=1.1; extra == "fast"
Requires-Dist: cchardet>=2.1; extra == "fast"
Requires-Dist: ciso8601; extra == "fast"
Requires-Dist: cython; extra == "fast"
Requires-Dist: orjson<3.0,>=2.0; extra == "fast"
Requires-Dist: setproctitle>=1.1; extra == "fast"
Provides-Extra: uvloop
Requires-Dist: uvloop>=0.8.1; extra == "uvloop"
Provides-Extra: datadog
Requires-Dist: datadog; extra == "datadog"
Provides-Extra: rocksdict
Requires-Dist: rocksdict<4.0,>=0.3.25; extra == "rocksdict"
Provides-Extra: setproctitle
Requires-Dist: setproctitle>=1.1; extra == "setproctitle"
Provides-Extra: cchardet
Requires-Dist: cchardet>=2.1; extra == "cchardet"
Provides-Extra: debug
Requires-Dist: setproctitle>=1.1; extra == "debug"
Requires-Dist: aiomonitor>=0.4.4; extra == "debug"
Provides-Extra: aiodns
Requires-Dist: aiodns>=1.1; extra == "aiodns"
Provides-Extra: ckafka
Requires-Dist: confluent-kafka~=1.2.0; extra == "ckafka"
Provides-Extra: aiomonitor
Requires-Dist: aiomonitor>=0.4.4; extra == "aiomonitor"
Provides-Extra: yaml
Requires-Dist: pyyaml>=5.1; extra == "yaml"
Provides-Extra: orjson
Requires-Dist: orjson<3.0,>=2.0; extra == "orjson"
Provides-Extra: prometheus
Requires-Dist: prometheus-client<1.0,>=0.20; extra == "prometheus"
Provides-Extra: redis
Requires-Dist: aredis<2.0,>=1.1.3; extra == "redis"
Provides-Extra: statsd
Requires-Dist: statsd~=3.3.0; extra == "statsd"
Provides-Extra: rocksdb
Requires-Dist: python-rocksdb>=0.6.7; extra == "rocksdb"
Provides-Extra: cython
Requires-Dist: cython; extra == "cython"
Provides-Extra: ciso8601
Requires-Dist: ciso8601; extra == "ciso8601"
Provides-Extra: eventlet
Requires-Dist: aioeventlet~=0.5.1; extra == "eventlet"
Requires-Dist: dnspython; extra == "eventlet"
Dynamic: author
Dynamic: author-email
Dynamic: classifier
Dynamic: description
Dynamic: description-content-type
Dynamic: home-page
Dynamic: keywords
Dynamic: license
Dynamic: license-file
Dynamic: platform
Dynamic: project-url
Dynamic: provides-extra
Dynamic: requires-dist
Dynamic: requires-python
Dynamic: summary
